kstyle/kstyle.py
kami_style-0.1.dist-info/METADATA
kami_style-0.1.dist-info/WHEEL
kami_style-0.1.dist-info/top_level.txt
kami_style-0.1.dist-info/RECORD
