Metadata-Version: 2.1
Name: kami-style
Version: 0.1
Summary: Want make some style? This for you!
Author: _Kamikotto_
Author-email: kamikotto3@email.com
